Gui_lib/__init__.py
Gui_lib/main.py
Gui_lib/widgets.py
gui_lib-0.3.0.dist-info/METADATA
gui_lib-0.3.0.dist-info/WHEEL
gui_lib-0.3.0.dist-info/top_level.txt
gui_lib-0.3.0.dist-info/RECORD
